clickupython/__init__.py
clickupython/client.py
clickupython/exceptions.py
clickupython/models.py
clickupython/helpers/__init__.py
clickupython/helpers/formatting.py
clickupython/helpers/timefuncs.py
tests/__init__.py
tests/test_client.py
tests/test_timefuncs.py
clickupython-1.0.4.dist-info/METADATA
clickupython-1.0.4.dist-info/WHEEL
clickupython-1.0.4.dist-info/top_level.txt
clickupython-1.0.4.dist-info/RECORD
