Metadata-Version: 2.1
Name: clickupython
Version: 1.0.4
Summary: clickupython: A Python client for the ClickUp API
Home-page: https://github.com/Imzachjohnson/clickupython
Author: Zach Johnson & Robert Mullis
Author-email: imzachjohnson@gmail.com
License: UNKNOWN
Project-URL: Documentation, https://clickupython.readthedocs.io/en/latest/
Project-URL: Bug Reports, https://github.com/Imzachjohnson/clickupython/issues
Project-URL: Source Code, https://github.com/Imzachjohnson/clickupython
Keywords: clickup,clickup api,python,clickupython
Platform: UNKNOWN
Requires-Python: >=3.6
Requires-Dist: pydantic (==1.8.2)
Requires-Dist: typing-extensions (==3.10.0.2)
Requires-Dist: word2number (==1.1)
Requires-Dist: timefhuman (==0.0.5)
Requires-Dist: pendulum (==2.1.2)
Requires-Dist: setuptools
